maze_world/__init__.py
maze_world/envs/__init__.py
maze_world/envs/maze.py
maze_world/envs/random_maze.py
maze_world/utils/__init__.py
maze_world/utils/generate_maze.py
maze_world/utils/solver.py
tests/__init__.py
maze_world-0.0.1.dist-info/LICENSE
maze_world-0.0.1.dist-info/METADATA
maze_world-0.0.1.dist-info/WHEEL
maze_world-0.0.1.dist-info/top_level.txt
maze_world-0.0.1.dist-info/RECORD
