Metadata-Version: 2.1
Name: maze-world
Version: 0.0.1
Summary: Random maze environments with different size and complexity for reinforcement learning and planning research. This is in-particular to investigate generalization and planning ability in dynamically changing environment.
Home-page: https://github.com/koulanurag/maze-world
Author: Anurag Koul
Author-email: koulanurag@gmail.com
License: MIT License
Classifier: Programming Language :: Python :: 3.6
Classifier: Programming Language :: Python :: 3.7
Classifier: Programming Language :: Python :: 3.8
Classifier: Programming Language :: Python :: 3.9
Classifier: Programming Language :: Python :: 3.10
Classifier: Programming Language :: Python :: 3.11
Requires-Python: >=3.6, <3.12
License-File: LICENSE
Requires-Dist: gymnasium >=0.28
Requires-Dist: pygame >=2.1.0
Requires-Dist: scipy
Requires-Dist: matplotlib
Provides-Extra: all
Requires-Dist: pytest <8.0.0 ; extra == 'all'
Requires-Dist: pytest-cases ; extra == 'all'
Requires-Dist: xdoctest ; extra == 'all'
Requires-Dist: pytest-cov ; extra == 'all'
Requires-Dist: black ; extra == 'all'
Requires-Dist: imageio ; extra == 'all'
Requires-Dist: jupyter ; extra == 'all'
Requires-Dist: black[jupyter] ; extra == 'all'
Requires-Dist: Sphinx <6.0,>=4.0 ; extra == 'all'
Requires-Dist: furo ; extra == 'all'
Requires-Dist: sphinxcontrib-katex ; extra == 'all'
Requires-Dist: sphinx-copybutton ; extra == 'all'
Requires-Dist: sphinx-design ; extra == 'all'
Requires-Dist: myst-parser ; extra == 'all'
Requires-Dist: sphinx-autobuild ; extra == 'all'
Requires-Dist: sphinxext-opengraph ; extra == 'all'
Requires-Dist: sphinx-prompt ; extra == 'all'
Requires-Dist: sphinx-favicon ; extra == 'all'
Requires-Dist: nbsphinx >=0.9.3 ; extra == 'all'
Requires-Dist: pandoc >=2.3 ; extra == 'all'
Requires-Dist: myst-nb ; extra == 'all'
Provides-Extra: develop
Requires-Dist: black ; extra == 'develop'
Requires-Dist: imageio ; extra == 'develop'
Requires-Dist: jupyter ; extra == 'develop'
Requires-Dist: black[jupyter] ; extra == 'develop'
Provides-Extra: docs
Requires-Dist: Sphinx <6.0,>=4.0 ; extra == 'docs'
Requires-Dist: furo ; extra == 'docs'
Requires-Dist: sphinxcontrib-katex ; extra == 'docs'
Requires-Dist: sphinx-copybutton ; extra == 'docs'
Requires-Dist: sphinx-design ; extra == 'docs'
Requires-Dist: myst-parser ; extra == 'docs'
Requires-Dist: sphinx-autobuild ; extra == 'docs'
Requires-Dist: sphinxext-opengraph ; extra == 'docs'
Requires-Dist: sphinx-prompt ; extra == 'docs'
Requires-Dist: sphinx-favicon ; extra == 'docs'
Requires-Dist: nbsphinx >=0.9.3 ; extra == 'docs'
Requires-Dist: pandoc >=2.3 ; extra == 'docs'
Requires-Dist: myst-nb ; extra == 'docs'
Provides-Extra: test
Requires-Dist: pytest <8.0.0 ; extra == 'test'
Requires-Dist: pytest-cases ; extra == 'test'
Requires-Dist: xdoctest ; extra == 'test'
Requires-Dist: pytest-cov ; extra == 'test'
